core/s3namic.py
s3namic/__init__.py
s3namic/core.py
s3namic-0.0.5.dist-info/LICENSE
s3namic-0.0.5.dist-info/METADATA
s3namic-0.0.5.dist-info/WHEEL
s3namic-0.0.5.dist-info/top_level.txt
s3namic-0.0.5.dist-info/RECORD
