Metadata-Version: 2.1
Name: s3namic
Version: 0.0.5
Summary: A Python package for managing AWS S3 bucket
Home-page: https://github.com/hyoj0942/s3namic
Author: Joey Kim
Author-email: hyoj0942@gmail.com
License: MIT
Keywords: aws,s3,bucket,management
License-File: LICENSE
Requires-Dist: pandas
Requires-Dist: boto3
Requires-Dist: botocore
Requires-Dist: pyarrow
